moai_adk/__init__.py
moai_adk/__main__.py
moai_adk/py.typed
moai_adk/version.py
moai_adk/astgrep/__init__.py
moai_adk/astgrep/analyzer.py
moai_adk/astgrep/models.py
moai_adk/astgrep/rules.py
moai_adk/cli/__init__.py
moai_adk/cli/main.py
moai_adk/cli/spec_status.py
moai_adk/cli/commands/__init__.py
moai_adk/cli/commands/analyze.py
moai_adk/cli/commands/doctor.py
moai_adk/cli/commands/init.py
moai_adk/cli/commands/language.py
moai_adk/cli/commands/lsp_setup.py
moai_adk/cli/commands/rank.py
moai_adk/cli/commands/status.py
moai_adk/cli/commands/switch.py
moai_adk/cli/commands/update.py
moai_adk/cli/prompts/__init__.py
moai_adk/cli/prompts/init_prompts.py
moai_adk/cli/prompts/translations/__init__.py
moai_adk/cli/ui/__init__.py
moai_adk/cli/ui/progress.py
moai_adk/cli/ui/prompts.py
moai_adk/cli/ui/theme.py
moai_adk/cli/worktree/__init__.py
moai_adk/cli/worktree/__main__.py
moai_adk/cli/worktree/cli.py
moai_adk/cli/worktree/exceptions.py
moai_adk/cli/worktree/manager.py
moai_adk/cli/worktree/models.py
moai_adk/cli/worktree/registry.py
moai_adk/core/PHASE2_OPTIMIZATIONS.md
moai_adk/core/__init__.py
moai_adk/core/claude_integration.py
moai_adk/core/command_helpers.py
moai_adk/core/comprehensive_monitoring_system.py
moai_adk/core/context_manager.py
moai_adk/core/credentials.py
moai_adk/core/enterprise_features.py
moai_adk/core/error_recovery_system.py
moai_adk/core/event_driven_hook_system.py
moai_adk/core/input_validation_middleware.py
moai_adk/core/issue_creator.py
moai_adk/core/jit_context_loader.py
moai_adk/core/jit_enhanced_hook_manager.py
moai_adk/core/language_config.py
moai_adk/core/language_config_resolver.py
moai_adk/core/language_validator.py
moai_adk/core/model_allocator.py
moai_adk/core/phase_optimized_hook_scheduler.py
moai_adk/core/realtime_monitoring_dashboard.py
moai_adk/core/robust_json_parser.py
moai_adk/core/rollback_manager.py
moai_adk/core/rules_loader.py
moai_adk/core/session_manager.py
moai_adk/core/skill_loading_system.py
moai_adk-1.14.0.dist-info/METADATA
moai_adk-1.14.0.dist-info/WHEEL
moai_adk-1.14.0.dist-info/entry_points.txt
moai_adk-1.14.0.dist-info/licenses/LICENSE
moai_adk-1.14.0.dist-info/RECORD
