Metadata-Version: 2.4
Name: moai-adk
Version: 1.14.0
Summary: MoAI Agentic Development Kit - SPEC-First DDD with Alfred SuperAgent & Unified moai-core-* Skills
Project-URL: Homepage, https://github.com/modu-ai/moai-adk
Project-URL: Repository, https://github.com/modu-ai/moai-adk
Project-URL: Issues, https://github.com/modu-ai/moai-adk/issues
Project-URL: Changelog, https://github.com/modu-ai/moai-adk/releases
Author-email: MoAI Team <support@moduai.kr>
License: COPYLEFT-3.0
License-File: LICENSE
Keywords: agentic,ai,alfred,claude,ddd,development,spec-first,toolkit
Classifier: Development Status :: 5 - Production/Stable
Classifier: Intended Audience :: Developers
Classifier: License :: Other/Proprietary License
Classifier: Operating System :: MacOS
Classifier: Operating System :: Microsoft :: Windows :: Windows 10
Classifier: Operating System :: Microsoft :: Windows :: Windows 11
Classifier: Operating System :: OS Independent
Classifier: Operating System :: POSIX :: Linux
Classifier: Programming Language :: Python :: 3
Classifier: Programming Language :: Python :: 3.11
Classifier: Programming Language :: Python :: 3.12
Classifier: Programming Language :: Python :: 3.13
Classifier: Programming Language :: Python :: 3.14
Classifier: Topic :: Software Development :: Libraries :: Python Modules
Classifier: Topic :: Software Development :: Quality Assurance
Classifier: Topic :: Software Development :: Testing
Requires-Python: >=3.11
Requires-Dist: aiohttp>=3.13.2
Requires-Dist: click>=8.1.0
Requires-Dist: gitpython>=3.1.45
Requires-Dist: inquirerpy>=0.3.4
Requires-Dist: jinja2>=3.0.0
Requires-Dist: packaging>=21.0
Requires-Dist: psutil>=7.1.3
Requires-Dist: pyfiglet>=1.0.2
Requires-Dist: pyyaml>=6.0
Requires-Dist: questionary>=2.0.0
Requires-Dist: requests>=2.28.0
Requires-Dist: rich>=13.0.0
Provides-Extra: dev
Requires-Dist: black>=24.0.0; extra == 'dev'
Requires-Dist: hypothesis>=6.100.0; extra == 'dev'
Requires-Dist: mypy>=1.7.0; extra == 'dev'
Requires-Dist: pytest-asyncio>=1.2.0; extra == 'dev'
Requires-Dist: pytest-benchmark>=4.0.0; extra == 'dev'
Requires-Dist: pytest-cov>=7.0.0; extra == 'dev'
Requires-Dist: pytest-mock>=3.15.1; extra == 'dev'
Requires-Dist: pytest-xdist>=3.8.0; extra == 'dev'
Requires-Dist: pytest<9.0.0,>=8.4.2; extra == 'dev'
Requires-Dist: ruff>=0.1.0; extra == 'dev'
Requires-Dist: types-pyyaml>=6.0.0; extra == 'dev'
Requires-Dist: types-requests>=2.28.0; extra == 'dev'
Provides-Extra: security
Requires-Dist: bandit>=1.8.0; extra == 'security'
Requires-Dist: pip-audit>=2.7.0; extra == 'security'
